transfersh_client/__init__.py
transfershclient-1.2.1.data/scripts/transfer
transfershclient-1.2.1.data/scripts/transfer-config
transfershclient-1.2.1.dist-info/DESCRIPTION.rst
transfershclient-1.2.1.dist-info/METADATA
transfershclient-1.2.1.dist-info/RECORD
transfershclient-1.2.1.dist-info/WHEEL
transfershclient-1.2.1.dist-info/metadata.json
transfershclient-1.2.1.dist-info/top_level.txt
