Metadata-Version: 2.0
Name: transfershclient
Version: 1.2.1
Summary: Command line tool for Transfer.sh server
Home-page: https://github.com/oscarsix/transfersh-client
Author: Oskar Malnowicz
Author-email: oscarsix@protonmail.ch
License: MIT
Platform: UNKNOWN
Requires-Python: >=3.4
Requires-Dist: requests
